{
    "resources": [
      {
        "index": "0",
        "title": "Ryzen 7",
        "link": "http://localhost:3000/item",
        "imageUrl": "https://www.mimovrste.com/i/43220161",
        "cena": "100€"
      },
      {
        "index": "1",
        "title": "Ryzen 7",
        "link": "http://localhost:3000/item",
        "imageUrl": "https://www.tradeinn.com/f/13795/137954422/amd-ryzen-7-5800x-3.8ghz-cpu.jpg",
        "cena": "120€"
      },
      {
        "index": "2",
        "title": "Ryzen 9",
        "link": "http://localhost:3000/item",
        "imageUrl": "https://www.mimovrste.com/i/52633571/550/550",
        "cena": "140€"
      },
      {
        "index": "3",
        "title": "Ryzen 9",
        "link": "http://localhost:3000/item",
        "imageUrl": "https://m.media-amazon.com/images/I/71S31CWSs3L._AC_SL1093_.jpg",
        "cena": "160€"
      },
      {
        "index": "4",
        "title": "Intel 9",
        "link": "http://localhost:3000/item",
        "imageUrl": "https://www.mimovrste.com/i/48822525/550/550",
        "cena": "180€"
      },
      {
        "index": "5",
        "title": "Intel 9",
        "link": "http://localhost:3000/item",
        "imageUrl": "https://m.media-amazon.com/images/I/613CfTnpwoL._AC_SX450_.jpg",
        "cena": "200€"
      }
    ]
  }
  